{"Title":"Electron microscopy images and morphometric data of SARS-CoV-2 variants in ultrathin plastic sections - Dataset 03 (SARS-CoV-2 Alpha B.1.1.7)","Dataset ID":"13136743","Timestemp":"2025-05-15T05:02:31+0000","Versions":1,"Views":292,"Unique Views":137,"Downloads":14,"Unique Downloads":13,"Github Name":"none"}
{"Title":"Electron microscopy images and morphometric data of SARS-CoV-2 variants in ultrathin plastic sections - Dataset 06 (SARS-CoV-2 Omicron B.1.1.529; BA.2)","Dataset ID":"13136319","Timestemp":"2025-05-15T05:02:31+0000","Versions":1,"Views":296,"Unique Views":125,"Downloads":18,"Unique Downloads":16,"Github Name":"none"}
{"Title":"SARS-CoV-2-PCR-Testungen in Deutschland","Dataset ID":"7193694","Timestemp":"2025-05-15T05:02:31+0000","Versions":34,"Views":3742,"Unique Views":3655,"Downloads":2602,"Unique Downloads":2212,"Github Name":"SARS-CoV-2-PCR-Testungen_in_Deutschland"}
{"Title":"Respiratorische Synzytialvirusf\u00e4lle in Deutschland","Dataset ID":"10816725","Timestemp":"2025-05-15T05:02:31+0000","Versions":60,"Views":5663,"Unique Views":2406,"Downloads":5378,"Unique Downloads":3840,"Github Name":"Respiratorische_Synzytialvirusfaelle_in_Deutschland"}
{"Title":"Corona-Datenspende - Teildatensatz Vitaldaten","Dataset ID":"8229283","Timestemp":"2025-05-15T05:02:31+0000","Versions":1,"Views":456,"Unique Views":417,"Downloads":601,"Unique Downloads":520,"Github Name":"Corona-Datenspende_Teildatensatz_Vitaldaten"}
{"Title":"Hochfrequente Mental Health Surveillance","Dataset ID":"8186447","Timestemp":"2025-05-15T05:02:31+0000","Versions":10,"Views":2047,"Unique Views":1941,"Downloads":1119,"Unique Downloads":987,"Github Name":"Hochfrequente_Mental_Health_Surveillance"}
{"Title":"Gesundheitsberichterstattung - Daten zu nicht \u00fcbertragbaren Erkrankungen","Dataset ID":"13736662","Timestemp":"2025-05-15T05:02:31+0000","Versions":1,"Views":652,"Unique Views":560,"Downloads":942,"Unique Downloads":682,"Github Name":"Gesundheitsberichterstattung_-_Daten_zu_nichtuebertragbaren_Erkrankungen"}
{"Title":"Abwassersurveillance AMELAG","Dataset ID":"10782701","Timestemp":"2025-05-15T05:02:31+0000","Versions":58,"Views":6363,"Unique Views":5916,"Downloads":18729,"Unique Downloads":9152,"Github Name":"Abwassersurveillance_AMELAG"}
{"Title":"SARS-CoV-2 Infektionen in Deutschland","Dataset ID":"4681153","Timestemp":"2025-05-15T05:02:31+0000","Versions":1302,"Views":112638,"Unique Views":109371,"Downloads":63526,"Unique Downloads":57657,"Github Name":"SARS-CoV-2-Infektionen_in_Deutschland"}
{"Title":"COVID-19-Impfungen in Deutschland","Dataset ID":"5126651","Timestemp":"2025-05-15T05:02:31+0000","Versions":560,"Views":65300,"Unique Views":63634,"Downloads":17900,"Unique Downloads":16100,"Github Name":"COVID-19-Impfungen_in_Deutschland"}
{"Title":"Appendix - Potential COVID-19 test fraud detection: Findings from a pilot study comparing conventional and statistical approaches","Dataset ID":"10608925","Timestemp":"2025-05-15T05:02:31+0000","Versions":3,"Views":655,"Unique Views":555,"Downloads":1297,"Unique Downloads":1187,"Github Name":"Appendix_Potential_COVID-19_test_fraud_detection"}
{"Title":"Electron microscopy images and morphometric data of SARS-CoV-2 variants in ultrathin plastic sections - Dataset 01 (SARS-CoV-2 Munich929)","Dataset ID":"13121515","Timestemp":"2025-05-15T05:02:31+0000","Versions":1,"Views":296,"Unique Views":116,"Downloads":12,"Unique Downloads":11,"Github Name":"none"}
{"Title":"7-Tage-Inzidenz der COVID-19-F\u00e4lle in Deutschland","Dataset ID":"7129007","Timestemp":"2025-05-15T05:02:31+0000","Versions":873,"Views":59922,"Unique Views":58600,"Downloads":62501,"Unique Downloads":56519,"Github Name":"COVID-19_7-Tage-Inzidenz_in_Deutschland"}
{"Title":"COVID-19-Todesf\u00e4lle in Deutschland","Dataset ID":"7127831","Timestemp":"2025-05-15T05:02:31+0000","Versions":845,"Views":57545,"Unique Views":53225,"Downloads":44919,"Unique Downloads":40600,"Github Name":"COVID-19-Todesfaelle_in_Deutschland"}
{"Title":"SARS-CoV-2 Sequenzdaten aus Deutschland","Dataset ID":"5139363","Timestemp":"2025-05-15T05:02:31+0000","Versions":715,"Views":70064,"Unique Views":68868,"Downloads":25892,"Unique Downloads":24884,"Github Name":"SARS-CoV-2-Sequenzdaten_aus_Deutschland"}
{"Title":"COVID-ARE-Konsultationsinzidenz","Dataset ID":"7221096","Timestemp":"2025-05-15T05:02:31+0000","Versions":132,"Views":8890,"Unique Views":8665,"Downloads":4653,"Unique Downloads":4408,"Github Name":"COVID-ARE-Konsultationsinzidenz"}
{"Title":"Reference percentiles for carotid measures of subclinical atherosclerosis in children and adolescents \u2013 Data from the KiGGS study","Dataset ID":"7048173","Timestemp":"2025-05-15T05:02:31+0000","Versions":1,"Views":178,"Unique Views":134,"Downloads":338,"Unique Downloads":309,"Github Name":"Carotid_intima-media_thickness-Reference_percentiles_from_the_KiGGS_study"}
{"Title":"Laborbest\u00e4tigte Influenzaf\u00e4lle in Deutschland","Dataset ID":"10401796","Timestemp":"2025-05-15T05:02:31+0000","Versions":72,"Views":3333,"Unique Views":3175,"Downloads":4990,"Unique Downloads":4184,"Github Name":"Influenzafaelle_in_Deutschland"}
{"Title":"AKTIN - Daten zur Aufenthaltsdauer in Notaufnahmen","Dataset ID":"7711111","Timestemp":"2025-05-15T05:02:31+0000","Versions":102,"Views":7406,"Unique Views":7186,"Downloads":3393,"Unique Downloads":3221,"Github Name":"AKTIN_Daten_zur_Aufenthaltsdauer_in_Notaufnahmen"}
{"Title":"Electron microscopy images and morphometric data of SARS-CoV-2 variants in ultrathin plastic sections - Dataset 05 (SARS-CoV-2 Delta B.1.617.2)","Dataset ID":"13136808","Timestemp":"2025-05-15T05:02:31+0000","Versions":1,"Views":277,"Unique Views":105,"Downloads":11,"Unique Downloads":10,"Github Name":"none"}
{"Title":"Polioviren im Abwasser - PIA","Dataset ID":"7680568","Timestemp":"2025-05-15T05:02:31+0000","Versions":2,"Views":486,"Unique Views":454,"Downloads":459,"Unique Downloads":362,"Github Name":"Polioviren_im_Abwasser-PIA"}
{"Title":"Inanspruchnahme von Routineimpfungen in Deutschland - Ergebnisse aus der KV-Impfsurveillance","Dataset ID":"10221305","Timestemp":"2025-05-15T05:02:31+0000","Versions":12,"Views":1525,"Unique Views":1256,"Downloads":2164,"Unique Downloads":1834,"Github Name":"Inanspruchnahme_von_Routineimpfungen_in_Deutschland-Ergebnisse_aus_der_KV-Impfsurveillance"}
{"Title":"Intensivkapazit\u00e4ten und COVID-19-Intensivbettenbelegung in Deutschland","Dataset ID":"7125598","Timestemp":"2025-05-15T05:02:31+0000","Versions":884,"Views":59724,"Unique Views":58503,"Downloads":66954,"Unique Downloads":62362,"Github Name":"Intensivkapazitaeten_und_COVID-19-Intensivbettenbelegung_in_Deutschland"}
{"Title":"SARI-Hospitalisierungsinzidenz","Dataset ID":"8382330","Timestemp":"2025-05-15T05:02:31+0000","Versions":83,"Views":6173,"Unique Views":5821,"Downloads":4764,"Unique Downloads":4289,"Github Name":"SARI-Hospitalisierungsinzidenz"}
{"Title":"COVID-SARI-Hospitalisierungsinzidenz","Dataset ID":"7234081","Timestemp":"2025-05-15T05:02:31+0000","Versions":105,"Views":8342,"Unique Views":8077,"Downloads":5291,"Unique Downloads":5039,"Github Name":"COVID-SARI-Hospitalisierungsinzidenz"}
{"Title":"ESI-CorA: SARS-CoV-2-Abwassersurveillance","Dataset ID":"10781652","Timestemp":"2025-05-15T05:02:31+0000","Versions":1,"Views":296,"Unique Views":280,"Downloads":488,"Unique Downloads":459,"Github Name":"ESI-CorA_SARS-CoV-2-Abwassersurveillance"}
{"Title":"Electron microscopy images and morphometric data of SARS-CoV-2 variants in ultrathin plastic sections - Dataset 02 (SARS-CoV-2 Italy-INMI1)","Dataset ID":"13136111","Timestemp":"2025-05-15T05:02:31+0000","Versions":1,"Views":273,"Unique Views":105,"Downloads":15,"Unique Downloads":14,"Github Name":"none"}
{"Title":"StopptCOVID-Studie - Daten, Analyse und Ergebnisse","Dataset ID":"10888032","Timestemp":"2025-05-15T05:02:31+0000","Versions":1,"Views":516,"Unique Views":465,"Downloads":876,"Unique Downloads":747,"Github Name":"StopptCOVID-Studie_Daten_Analyse_und_Ergebnisse"}
{"Title":"Bundesweiter klinischer Krebsregisterdatensatz - Datenschema und Klassifikationen","Dataset ID":"10022039","Timestemp":"2025-05-15T05:02:31+0000","Versions":1,"Views":389,"Unique Views":312,"Downloads":459,"Unique Downloads":450,"Github Name":"Bundesweiter_klinischer_Krebsregisterdatensatz-Datenschema_und_Klassifikationen"}
{"Title":"Corona-Datenspende - Teildatensatz Erleben und Verhalten in der Pandemie","Dataset ID":"7185198","Timestemp":"2025-05-15T05:02:31+0000","Versions":1,"Views":898,"Unique Views":834,"Downloads":389,"Unique Downloads":312,"Github Name":"Corona-Datenspende_Teildatensatz_Erleben_und_Verhalten_in_der_Pandemie"}
{"Title":"Electron microscopy images and morphometric data of SARS-CoV-2 variants in ultrathin plastic sections - Dataset 04 (SARS-CoV-2 Beta B.1.351)","Dataset ID":"13136766","Timestemp":"2025-05-15T05:02:31+0000","Versions":1,"Views":94,"Unique Views":80,"Downloads":4,"Unique Downloads":4,"Github Name":"none"}
{"Title":"Gesundheit in Deutschland aktuell - GEDA 2019\/2020-EHIS","Dataset ID":"6036771","Timestemp":"2025-05-15T05:02:31+0000","Versions":6,"Views":2123,"Unique Views":1886,"Downloads":1132,"Unique Downloads":881,"Github Name":"Gesundheit_in_Deutschland_Aktuell"}
{"Title":"EMViR - Electron Microscopy Image Dataset of Labelled Respiratory Viruses for Deep Learning Model Development","Dataset ID":"13949330","Timestemp":"2025-05-15T05:02:31+0000","Versions":1,"Views":172,"Unique Views":136,"Downloads":61,"Unique Downloads":54,"Github Name":"none"}
{"Title":"Ergebnisdatensatz BURDEN 2020 \u2013 Krankheitslast in Deutschland und seinen Regionen","Dataset ID":"7323765","Timestemp":"2025-05-15T05:02:31+0000","Versions":3,"Views":2650,"Unique Views":2506,"Downloads":1474,"Unique Downloads":1130,"Github Name":"BURDEN_2020_-_Krankheitslast_in_Deutschland_und_seinen_Regionen"}
{"Title":"German Index of Socioeconomic Deprivation (GISD)","Dataset ID":"6840303","Timestemp":"2025-05-15T05:02:31+0000","Versions":7,"Views":4961,"Unique Views":4332,"Downloads":4392,"Unique Downloads":3390,"Github Name":"German_Index_of_Socioeconomic_Deprivation_GISD"}
{"Title":"GrippeWeb - Daten des Wochenberichts","Dataset ID":"8340322","Timestemp":"2025-05-15T05:02:31+0000","Versions":88,"Views":12605,"Unique Views":11867,"Downloads":11512,"Unique Downloads":10118,"Github Name":"GrippeWeb_Daten_des_Wochenberichts"}
{"Title":"Epylabel: Ensemble-labeling of infectious diseases time series","Dataset ID":"12665039","Timestemp":"2025-05-15T05:02:31+0000","Versions":1,"Views":238,"Unique Views":97,"Downloads":71,"Unique Downloads":64,"Github Name":"epylabel"}
{"Title":"Observatorium serologischer Studien zu SARS-CoV-2 in Deutschland","Dataset ID":"7043024","Timestemp":"2025-05-15T05:02:31+0000","Versions":1,"Views":714,"Unique Views":659,"Downloads":702,"Unique Downloads":658,"Github Name":"Observatorium_serologischer_Studien_zu_SARS-CoV-2_in_Deutschland"}
{"Title":"Daten der Notaufnahmesurveillance","Dataset ID":"7189871","Timestemp":"2025-05-15T05:02:31+0000","Versions":523,"Views":27877,"Unique Views":27157,"Downloads":39638,"Unique Downloads":37946,"Github Name":"Daten_der_Notaufnahmesurveillance"}
{"Title":"COVID-19-Hospitalisierungen in Deutschland","Dataset ID":"5519056","Timestemp":"2025-05-15T05:02:31+0000","Versions":1215,"Views":107670,"Unique Views":104534,"Downloads":48983,"Unique Downloads":45846,"Github Name":"COVID-19-Hospitalisierungen_in_Deutschland"}
{"Title":"SARS-CoV-2-Nowcasting und -R-Schaetzung","Dataset ID":"4680400","Timestemp":"2025-05-15T05:02:31+0000","Versions":748,"Views":76942,"Unique Views":76091,"Downloads":34871,"Unique Downloads":33456,"Github Name":"SARS-CoV-2-Nowcasting_und_-R-Schaetzung"}
{"Title":"ARE-Konsultationsinzidenz","Dataset ID":"8340315","Timestemp":"2025-05-15T05:02:31+0000","Versions":84,"Views":5711,"Unique Views":5400,"Downloads":3876,"Unique Downloads":3545,"Github Name":"ARE-Konsultationsinzidenz"}
