{"views":null,"unique_views":null,"clones":null,"unique_clones":null,"repository":"krllzr\/barzooka","timestamp":1728047927665,"stargazers_count":0,"watchers_count":0,"forks_count":0,"open_issues_count":0,"size":8281,"subscribers_count":0,"views_diff":null,"unique_views_diff":null,"clones_diff":null,"unique_clones_diff":null}
{"views":null,"unique_views":null,"clones":null,"unique_clones":null,"repository":"krllzr\/OpenDataStint","timestamp":1728047927665,"stargazers_count":0,"watchers_count":0,"forks_count":0,"open_issues_count":0,"size":292,"subscribers_count":2,"views_diff":null,"unique_views_diff":null,"clones_diff":null,"unique_clones_diff":null}
{"views":13.0,"unique_views":2.0,"clones":0.0,"unique_clones":0.0,"repository":"krllzr\/barzooka","timestamp":1728048024099,"stargazers_count":0,"watchers_count":0,"forks_count":0,"open_issues_count":0,"size":8281,"subscribers_count":0,"views_diff":null,"unique_views_diff":null,"clones_diff":null,"unique_clones_diff":null}
{"views":358.0,"unique_views":1.0,"clones":101.0,"unique_clones":47.0,"repository":"krllzr\/OpenDataStint","timestamp":1728048024099,"stargazers_count":0,"watchers_count":0,"forks_count":0,"open_issues_count":0,"size":292,"subscribers_count":2,"views_diff":null,"unique_views_diff":null,"clones_diff":null,"unique_clones_diff":null}
{"views":13.0,"unique_views":2.0,"clones":0.0,"unique_clones":0.0,"repository":"krllzr\/barzooka","timestamp":1728048144626,"stargazers_count":0,"watchers_count":0,"forks_count":0,"open_issues_count":0,"size":8281,"subscribers_count":0,"views_diff":0.0,"unique_views_diff":0.0,"clones_diff":0.0,"unique_clones_diff":0.0}
{"views":358.0,"unique_views":1.0,"clones":101.0,"unique_clones":47.0,"repository":"krllzr\/OpenDataStint","timestamp":1728048144626,"stargazers_count":0,"watchers_count":0,"forks_count":0,"open_issues_count":0,"size":292,"subscribers_count":2,"views_diff":0.0,"unique_views_diff":0.0,"clones_diff":0.0,"unique_clones_diff":0.0}
